{
    "dataset_reader": {
        "type": null
    },
    "train_data_path": null,
    "validation_data_path": null,
    "model": {
        "type": "HAN",
        "text_field_embedder": {
            "token_embedders": {
                "tokens": {
                    "type": "embedding",
                    "embedding_dim": 200,
                    "trainable": true
                }
            }
        },
        "encoder": {
            "type": "HierarchicalAttention",
            "input_size": 200,
            "hidden_size": 200,
            "attention_size": 200,
            "device": null
        },
        "loss_weights": [
            0.1, 
            1.0
        ]
    },
    "iterator": {
        "type": "bucket",
        "sorting_keys": [
            [
                "tokens",
                "num_tokens"
            ]
        ],
        "padding_noise": 0,
        "batch_size": 2
    },
    "trainer": {
        "num_epochs": 15,
        "cuda_device": null,
        "grad_clipping": 1,
        "validation_metric": "+accuracy",
        "optimizer": {
            "type": "adam"
        }
    }
}
